Workbook

Sheet Sheet1
A1: information_date | B1: account_number | C1: pool2 | D1: pool | E1: attorney_name | F1: current_liability | G1: arrears_amount | H1: MIL | I1: mil_72 | J1: legal_ind | K1: Legal_Category | L1: MIL_BUCK | M1: SMJPLRCV_ind | N1: arms_ind | O1: zero_balance | P1: credit_balance | Q1: settlement_raw | R1: settlement_aggressive | S1: settlement_1 | T1: settlement_2 | U1: settlement_3 | V1: EXPOSURE_I9 | W1: expected_loss_i9 | X1: coverage | Y1: expected_recovery
A2: 46250 | B2: 50442209 | C2: Legal | D2: Small Balances between R100 and R200 | E2: Internal | F2: -48935.05 | G2: 0 | H2: 61 | I2: 0 | J2: late | K2: Litigation | L2: 60-65 | P2: 1 | Q2: 0.49297396 | R2: 0.49297396 | S2: 0.49297396 | T2: 0.64086615 | U2: 9.99 | X2: =W2/V2 -> #DIV/0!
A3: 46250 | B3: 50595358 | C3: Legal | D3: Deceased | E3: Velile Tinto & Associates Inc | F3: 315036.98 | G3: 315031.23 | H3: 133 | I3: 1 | J3: late | K3: Deceased | L3: 72+ | Q3: 0.010908657 | R3: 0.1 | S3: 0.25 | T3: 0.325 | U3: 0.325 | V3: 315031.23 | W3: 315031.23 | X3: =W3/V3 -> 1
A4: 46250 | B4: 50652580 | C4: Legal | D4: Charge_off_process | E4: Kemp and Associates | F4: 430573.01 | G4: 164462.03 | H4: 59 | I4: 0 | J4: late | K4: Deceased | L4: 54-59 | Q4: 0.28561154 | R4: 0.28561154 | S4: 0.28561154 | T4: 0.371295 | U4: 0.371295 | V4: 430504.01 | W4: 122742.66 | X4: =W4/V4 -> 0.28511387
A5: 46250 | B5: 50972879 | C5: Legal | E5: Strauss Daly Inc | F5: 0 | G5: -234888.53 | H5: 37 | I5: 0 | J5: late | K5: Litigation | L5: 36-41 | O5: 1 | X5: =W5/V5 -> #DIV/0!
A6: 46250 | B6: 50988325 | C6: Legal | D6: Charge_off_process | E6: Kemp and Associates | F6: 351037.43 | G6: 351037.43 | H6: 113 | I6: 1 | J6: late | K6: Deceased | L6: 72+ | Q6: 0.01977759 | R6: 0.1 | S6: 0.25 | T6: 0.325 | U6: 9.99 | V6: 351037.43 | W6: 351037.43 | X6: =W6/V6 -> 1
A7: 46250 | B7: 51115910 | C7: Legal | F7: 0 | G7: 0 | H7: 118 | I7: 1 | J7: late | K7: Litigation | L7: 72+ | O7: 1 | X7: =W7/V7 -> #DIV/0!
A8: 46250 | B8: 51416791 | C8: Legal | D8: Charge_off_process | E8: Kemp and Associates | F8: 290347.72 | G8: 290278.72 | H8: 61 | I8: 0 | J8: late | K8: Deceased | L8: 60-65 | Q8: 0.27536527 | R8: 0.27536527 | S8: 0.27536527 | T8: 0.35797485 | U8: 9.99 | V8: 290128.82 | W8: 175615.25 | X8: =W8/V8 -> 0.60530097
A9: 46250 | B9: 51591240 | C9: Legal | D9: Deceased | E9: Internal | F9: 1249617.3 | G9: 580387.84 | H9: 46 | I9: 0 | J9: late | K9: Deceased | L9: 42-47 | Q9: 0.42322386 | R9: 0.42322386 | S9: 0.42322386 | T9: 0.52902983 | U9: 0.52902983 | V9: 1244204.1 | W9: 412184.51 | X9: =W9/V9 -> 0.33128368
A10: 46250 | B10: 52072476 | C10: Legal | E10: Fourie Basson Veldtman | F10: 0 | G10: 0 | H10: 37 | I10: 0 | J10: late | K10: Litigation | L10: 36-41 | O10: 1 | X10: =W10/V10 -> #DIV/0!
A11: 46250 | B11: 52082862 | C11: Legal | E11: Sandenberg Nel Haggard | F11: 0 | G11: -1069060 | H11: 109 | I11: 1 | J11: late | K11: Litigation | L11: 72+ | O11: 1 | Q11: 0.022260488 | R11: 0.1 | S11: 0.25 | T11: 0.3125 | U11: 0.3125 | X11: =W11/V11 -> #DIV/0!
A12: 46250 | B12: 52254302 | C12: Legal | D12: Account in Legal Sales In Execution Proc | E12: Velile Tinto & Associates Inc | F12: 694565.55 | G12: 474731.77 | H12: 71 | I12: 0 | J12: late | K12: Litigation | L12: 65-71 | Q12: 0.28507187 | R12: 0.28507187 | S12: 0.28507187 | T12: 0.28507187 | U12: 0.28507187 | V12: 694286.95 | W12: 566369.46 | X12: =W12/V12 -> 0.81575703
A13: 46250 | B13: 52281989 | C13: Legal | D13: Deceased | E13: Velile Tinto & Associates Inc | F13: 924540.41 | G13: 924471.41 | H13: 107 | I13: 1 | J13: late | K13: Deceased | L13: 72+ | Q13: 0.023613729 | R13: 0.1 | S13: 0.25 | T13: 0.325 | U13: 9.99 | V13: 924471.41 | W13: 924471.41 | X13: =W13/V13 -> 1
A14: 46250 | B14: 52444594 | C14: Legal | D14: Deceased | F14: 296629.8 | G14: 296624.05 | H14: 88 | I14: 1 | J14: late | K14: Deceased | L14: 72+ | Q14: 0.04924842 | R14: 0.1 | S14: 0.25 | T14: 0.325 | U14: 0.325 | V14: 296624.05 | W14: 195277.71 | X14: =W14/V14 -> 0.65833404
A15: 46250 | B15: 52751306 | C15: Legal | D15: Deceased | E15: Velile Tinto & Associates Inc | F15: 330686.96 | G15: 330686.96 | H15: 103 | I15: 1 | J15: late | K15: Deceased | L15: 72+ | Q15: 0.026565168 | R15: 0.1 | S15: 0.25 | T15: 0.325 | U15: 0.325 | V15: 330686.96 | W15: 330686.96 | X15: =W15/V15 -> 1
A16: 46250 | B16: 54228015 | C16: Legal | E16: Strauss Daly Inc | F16: 0 | G16: 0 | H16: 48 | I16: 0 | J16: late | K16: Litigation | L16: 48-53 | O16: 1 | X16: =W16/V16 -> #DIV/0!
A17: 46250 | B17: 54345836 | C17: Legal | D17: Charge_off_process | E17: Kemp and Associates | F17: 172426.84 | G17: 172357.84 | H17: 68 | I17: 0 | J17: late | K17: Deceased | L17: 65-71 | Q17: 0.24374453 | R17: 0.24374453 | S17: 0.25 | T17: 0.325 | U17: 0.325 | V17: 172357.84 | W17: 106698.17 | X17: =W17/V17 -> 0.61905028
A18: 46250 | B18: 54372930 | C18: Legal | D18: Account in Legal Sales In Execution Proc | E18: Johnston and Partners | F18: 281375.14 | G18: 281375.14 | H18: 48 | I18: 0 | J18: late | K18: Litigation | L18: 48-53 | Q18: 0.41584028 | R18: 0.41584028 | S18: 0.41584028 | T18: 0.54059237 | U18: 0.54059237 | V18: 281375.14 | W18: 136499.42 | X18: =W18/V18 -> 0.48511543
A19: 46250 | B19: 54967063 | C19: Legal | D19: Deceased | E19: Vezi & De Beer | F19: 180567.78 | G19: 180562.03 | H19: 82 | I19: 1 | J19: late | K19: Deceased | L19: 72+ | Q19: 0.17959562 | R19: 0.17959562 | S19: 0.25 | T19: 0.3125 | U19: 9.99 | V19: 180562.03 | W19: 180562.03 | X19: =W19/V19 -> 1
A20: 46250 | B20: 54984189 | C20: Legal | D20: Charge_off_process | F20: 98999.79 | G20: 98930.79 | H20: 38 | I20: 0 | J20: late | K20: Deceased | L20: 36-41 | Q20: 0.50811232 | R20: 0.50811232 | S20: 0.50811232 | T20: 0.66054601 | U20: 9.99 | V20: 103902.59 | W20: 14617.562 | X20: =W20/V20 -> 0.14068525
A21: 46250 | B21: 55237522 | C21: Legal | E21: Vezi & De Beer | F21: 0 | G21: -217907.78 | H21: 56 | I21: 0 | J21: late | K21: Litigation | L21: 54-59 | O21: 1 | X21: =W21/V21 -> #DIV/0!
A22: 46250 | B22: 55688028 | C22: Legal | D22: Deceased | E22: Velile Tinto & Associates Inc | F22: 649123.45 | G22: 47360.49 | H22: 40 | I22: 0 | J22: late | K22: Deceased | L22: 36-41 | Q22: 0.46039277 | R22: 0.46039277 | S22: 0.46039277 | T22: 0.55247133 | U22: 0.55247133 | V22: 647388.88 | W22: 187370.76 | X22: =W22/V22 -> 0.28942535
A23: 46250 | B23: 55708118 | C23: Legal | D23: Charge_off_process | E23: Strauss Daly Inc | F23: 562493.96 | G23: 562488.21 | H23: 130 | I23: 1 | J23: late | K23: Deceased | L23: 72+ | Q23: 0.011930793 | R23: 0.1 | S23: 0.25 | T23: 0.3 | U23: 0.3 | V23: 562488.21 | W23: 562488.21 | X23: =W23/V23 -> 1
A24: 46250 | B24: 55812284 | C24: Legal | E24: Tim Du Toit Attorneys | F24: 0 | G24: 0 | H24: 36 | I24: 0 | J24: late | K24: Litigation | L24: 36-41 | O24: 1 | X24: =W24/V24 -> #DIV/0!
A25: 46250 | B25: 55843619 | C25: Legal | D25: Charge_off_process | E25: Poswa Inc | F25: 258624.23 | G25: 258555.23 | H25: 65 | I25: 0 | J25: late | K25: Litigation | L25: 60-65 | Q25: 0.35485408 | R25: 0.35485408 | S25: 0.35485408 | T25: 0.4613103 | U25: 9.99 | V25: 258488.48 | W25: 158494.21 | X25: =W25/V25 -> 0.61315772
A26: 46250 | B26: 56077790 | C26: Legal | F26: 0 | G26: 0 | H26: 58 | I26: 0 | J26: late | K26: Litigation | L26: 54-59 | O26: 1 | X26: =W26/V26 -> #DIV/0!
A27: 46250 | B27: 56109153 | C27: Legal | D27: Account in Legal Defended Matters Proces | E27: Velile Tinto & Associates Inc | F27: 1321769.2 | G27: 1321700.2 | H27: 130 | I27: 1 | J27: late | K27: Defended M | L27: 72+ | Q27: 0.13166991 | R27: 0.13166991 | S27: 0.25 | T27: 0.25 | U27: 9.99 | V27: 1321700.2 | W27: 1321700.2 | X27: =W27/V27 -> 1
A28: 46250 | B28: 56115773 | C28: Legal | D28: Deceased | E28: Velile Tinto & Associates Inc | F28: 185267.78 | G28: 30723.82 | H28: 42 | I28: 0 | J28: late | K28: Deceased | L28: 42-47 | Q28: 0.47973979 | R28: 0.47973979 | S28: 0.47973979 | T28: 0.62366173 | U28: 9.99 | V28: 184908.01 | W28: 32842.068 | X28: =W28/V28 -> 0.17761301
A29: 46250 | B29: 56270256 | C29: Legal | D29: Account in Legal Sales In Execution Proc | E29: Strauss Daly Inc | F29: 318298.04 | G29: 318292.29 | H29: 81 | I29: 1 | J29: late | K29: Deceased | L29: 72+ | Q29: 0.18363399 | R29: 0.18363399 | S29: 0.25 | T29: 0.325 | U29: 0.325 | V29: 318211.83 | W29: 318211.83 | X29: =W29/V29 -> 1
A30: 46250 | B30: 56291024 | C30: Legal | D30: Charge_off_process | E30: Velile Tinto & Associates Inc | F30: 820886.37 | G30: 820817.37 | H30: 46 | I30: 0 | J30: late | K30: Litigation | L30: 42-47 | Q30: 0.44408906 | R30: 0.44408906 | S30: 0.44408906 | T30: 0.57731577 | U30: 0.57731577 | V30: 818919.58 | W30: 251181.79 | X30: =W30/V30 -> 0.30672339
A31: 46250 | B31: 56318313 | C31: Legal | D31: Deceased | E31: Internal | F31: 429180.28 | G31: 312928.49 | H31: 41 | I31: 0 | J31: late | K31: Deceased | L31: 36-41 | Q31: 0.46593456 | R31: 0.46593456 | S31: 0.46593456 | T31: 0.60571493 | U31: 9.99 | V31: 430177.39 | W31: 107798.35 | X31: =W31/V31 -> 0.25059045
A32: 46250 | B32: 56391533 | C32: Legal | D32: Charge_off_process | F32: 244132.13 | G32: 34753.64 | H32: 70 | I32: 0 | J32: late | K32: Deceased | L32: 65-71 | Q32: 0.31974018 | R32: 0.31974018 | S32: 0.31974018 | T32: 0.41566223 | U32: 9.99 | V32: 235301.46 | W32: 51128.001 | X32: =W32/V32 -> 0.21728722
A33: 46250 | B33: 56408797 | C33: Legal | D33: Deceased | E33: Velile Tinto & Associates Inc | F33: 616702.73 | G33: 616702.73 | H33: 89 | I33: 1 | J33: late | K33: Deceased | L33: 72+ | Q33: 0.045911496 | R33: 0.1 | S33: 0.25 | T33: 0.3125 | U33: 9.99 | V33: 616702.73 | W33: 616702.73 | X33: =W33/V33 -> 1
A34: 46250 | B34: 56474757 | C34: Legal | D34: Deceased | E34: Velile Tinto & Associates Inc | F34: 364838.41 | G34: 364838.41 | H34: 121 | I34: 1 | J34: late | K34: Deceased | L34: 72+ | Q34: 0.015598947 | R34: 0.1 | S34: 0.25 | T34: 0.3125 | U34: 9.99 | V34: 364838.41 | W34: 364838.41 | X34: =W34/V34 -> 1
A35: 46250 | B35: 56706372 | C35: Legal | D35: Charge_off_process | E35: Velile Tinto & Associates Inc | F35: 70375.3 | G35: 53037.15 | H35: 101 | I35: 1 | J35: late | K35: Deceased | L35: 72+ | Q35: 0.028172555 | R35: 0.1 | S35: 0.25 | T35: 0.325 | U35: 0.325 | V35: 76804 | W35: 76804 | X35: =W35/V35 -> 1
A36: 46250 | B36: 56756337 | C36: Legal | D36: Small Balances between R100 and R200 | E36: Internal | F36: -1047.66 | G36: -432272.76 | H36: 46 | I36: 0 | J36: late | K36: Litigation | L36: 42-47 | P36: 1 | Q36: 0.45573165 | R36: 0.45573165 | S36: 0.45573165 | T36: 0.59245114 | U36: 9.99 | V36: 0 | W36: 0 | X36: =W36/V36 -> #DIV/0!
A37: 46250 | B37: 56974733 | C37: Legal | F37: 0 | G37: 0 | H37: 72 | I37: 1 | J37: late | K37: Litigation | L37: 72+ | O37: 1 | X37: =W37/V37 -> #DIV/0!
A38: 46250 | B38: 57133910 | C38: Legal | D38: Deceased | E38: Internal | F38: 301223.16 | G38: 301217.41 | H38: 104 | I38: 1 | J38: late | K38: Deceased | L38: 72+ | Q38: 0.1016444 | R38: 0.1016444 | S38: 0.25 | T38: 0.325 | U38: 0.325 | V38: 301217.41 | W38: 209096.55 | X38: =W38/V38 -> 0.69417151
A39: 46250 | B39: 57182261 | C39: Legal | D39: Deceased | E39: Kemp and Associates | F39: 254495.1 | G39: 254489.35 | H39: 77 | I39: 1 | J39: late | K39: Deceased | L39: 72+ | Q39: 0.20528726 | R39: 0.20528726 | S39: 0.25 | T39: 0.275 | U39: 9.99 | V39: 254489.35 | W39: 254489.35 | X39: =W39/V39 -> 1
A40: 46250 | B40: 57461438 | C40: Legal | D40: Charge_off_process | E40: Kemp and Associates | F40: 836252.85 | G40: 374378.54 | H40: 37 | I40: 0 | J40: late | K40: Deceased | L40: 36-41 | Q40: 0.48512777 | R40: 0.48512777 | S40: 0.48512777 | T40: 0.60640971 | U40: 0.60640971 | V40: 837077.65 | W40: 201186.73 | X40: =W40/V40 -> 0.24034416
A41: 46250 | B41: 57836695 | C41: Legal | D41: Charge_off_process | E41: Hack, Stupel & Ross | F41: 879778.37 | G41: 879772.68 | H41: 129 | I41: 1 | J41: late | K41: Litigation | L41: 72+ | Q41: 0.018917578 | R41: 0.1 | S41: 0.25 | T41: 0.3125 | U41: 9.99 | V41: 879772.68 | W41: 879772.68 | X41: =W41/V41 -> 1 | Y41: =R41*F41 -> 87977.837
A42: 46250 | B42: 58191736 | C42: Legal | D42: Charge_off_process | E42: Strauss Daly Inc | F42: 370761.58 | G42: 370692.58 | H42: 72 | I42: 1 | J42: late | K42: Deceased | L42: 72+ | Q42: 0.10678774 | R42: 0.10678774 | S42: 0.25 | T42: 0.325 | U42: 0.325 | V42: 370865.7 | W42: 370865.7 | X42: =W42/V42 -> 1
A43: 46250 | B43: 58222690 | C43: Legal | D43: Charge_off_process | E43: Strauss Daly Inc | F43: 226192.1 | G43: 155865.46 | H43: 67 | I43: 0 | J43: late | K43: Litigation | L43: 65-71 | Q43: 0.45235427 | R43: 0.45235427 | S43: 0.45235427 | T43: 0.58806055 | U43: 0.58806055 | V43: 229323.1 | W43: 39251.073 | X43: =W43/V43 -> 0.17116057
A44: 46250 | B44: 58264210 | C44: Legal | D44: Arms | E44: Internal | F44: -121.72 | G44: 0 | H44: 121 | I44: 1 | J44: late | K44: Litigation | L44: 72+ | N44: 1 | P44: 1 | X44: =W44/V44 -> #DIV/0!
A45: 46250 | B45: 58312290 | C45: Legal | E45: Strauss Daly Inc | F45: 0 | G45: -27301.58 | H45: 61 | I45: 0 | J45: late | K45: Litigation | L45: 60-65 | O45: 1 | X45: =W45/V45 -> #DIV/0!
A46: 46250 | B46: 58317705 | C46: Legal | F46: 0 | G46: 0 | H46: 84 | I46: 1 | J46: late | K46: Litigation | L46: 72+ | O46: 1 | X46: =W46/V46 -> #DIV/0!
A47: 46250 | B47: 58646237 | C47: Legal | D47: Deceased | E47: Sandenberg Nel Haggard | F47: 179426.3 | G47: 174109.57 | H47: 101 | I47: 1 | J47: late | K47: Deceased | L47: 72+ | Q47: 0.028172555 | R47: 0.1 | S47: 0.25 | T47: 0.325 | U47: 9.99 | V47: 174061.33 | W47: 174061.33 | X47: =W47/V47 -> 1
A48: 46250 | B48: 82099484 | C48: Legal | E48: Haasbroek & Boezaart Attorneys | F48: 0 | G48: 0 | H48: 55 | I48: 0 | J48: late | K48: Litigation | L48: 54-59 | O48: 1 | Q48: 0.39894106 | R48: 0.39894106 | S48: 0.39894106 | T48: 0.51862338 | U48: 0.51862338 | X48: =W48/V48 -> #DIV/0!
A49: 46250 | B49: 102019113 | C49: Legal | D49: Deceased | E49: Velile Tinto & Associates Inc | F49: 388614.64 | G49: 288736.01 | H49: 68 | I49: 0 | J49: late | K49: Deceased | L49: 65-71 | Q49: 0.24374453 | R49: 0.24374453 | S49: 0.25 | T49: 0.325 | U49: 9.99 | V49: 386876.01 | W49: 239495.7 | X49: =W49/V49 -> 0.61905028
A50: 46250 | B50: 1052057422 | C50: Legal | D50: Charge_off_process | E50: Smit Sewgoolam | F50: 7430329.2 | G50: 6077485.7 | H50: 102 | I50: 1 | J50: late | K50: Litigation | L50: 72+ | Q50: 0.10587513 | R50: 0.10587513 | S50: 0.25 | T50: 0.325 | U50: 0.325 | V50: 7430260.2 | W50: 7430260.2 | X50: =W50/V50 -> 1 | Y50: =R50*F50 -> 786687.08
A51: 46250 | B51: 1082056455 | C51: Legal | E51: Haasbroek & Boezaart Attorneys | F51: 0 | G51: -2026128.8 | H51: 65 | I51: 0 | J51: late | K51: Litigation | L51: 60-65 | O51: 1 | X51: =W51/V51 -> #DIV/0!
A52: 46250 | B52: 1082065721 | C52: Legal | E52: Poswa Inc | F52: 0 | G52: -1148031.1 | H52: 70 | I52: 0 | J52: late | K52: Litigation | L52: 65-71 | O52: 1 | Q52: 0.32741997 | R52: 0.32741997 | S52: 0.32741997 | T52: 0.42564597 | U52: 9.99 | X52: =W52/V52 -> #DIV/0!
A53: 46250 | B53: 2022002492 | C53: Legal | D53: Charge_off_process | E53: Hack, Stupel & Ross | F53: 560404.27 | G53: 375261.05 | H53: 53 | I53: 0 | J53: late | K53: Litigation | L53: 48-53 | Q53: 0.51036663 | R53: 0.51036663 | S53: 0.51036663 | T53: 0.66347662 | U53: 0.66347662 | V53: 563568.46 | W53: 117932.89 | X53: =W53/V53 -> 0.20926098
A54: 46250 | B54: 2062001936 | C54: Legal | D54: Account in Legal Defended Matters Applic | E54: Velile Tinto & Associates Inc | F54: 468308.7 | G54: 468239.7 | H54: 71 | I54: 0 | J54: late | K54: Defended M | L54: 65-71 | Q54: 0.29684709 | R54: 0.29684709 | S54: 0.29684709 | T54: 0.38590122 | U54: 0.38590122 | V54: 468128.28 | W54: 338519.12 | X54: =W54/V54 -> 0.72313325
A55: 46250 | B55: 2082022239 | C55: Legal | D55: Charge_off_process | E55: Smit Sewgoolam | F55: 313515.59 | G55: 313446.59 | H55: 59 | I55: 0 | J55: late | K55: Deceased | L55: 54-59 | Q55: 0.29844557 | R55: 0.29844557 | S55: 0.29844557 | T55: 0.38797924 | U55: 9.99 | V55: 312251.67 | W55: 175151.8 | X55: =W55/V55 -> 0.56093152
A56: 46250 | B56: 3092042560 | C56: Legal | D56: Arms | F56: -7.55 | G56: -7.55 | H56: 82 | I56: 1 | J56: late | K56: Litigation | L56: 72+ | N56: 1 | P56: 1 | X56: =W56/V56 -> #DIV/0!
A57: 46250 | B57: 4052027166 | C57: Legal | D57: Deceased | E57: Internal | F57: 402019.01 | G57: 402019.01 | H57: 120 | I57: 1 | J57: late | K57: Deceased | L57: 72+ | Q57: 0.046945949 | R57: 0.1 | S57: 0.25 | T57: 0.325 | U57: 0.325 | V57: 402019.01 | W57: 402019.01 | X57: =W57/V57 -> 1
A58: 46250 | B58: 4092066199 | C58: Legal | D58: Account in Legal Registration Process | E58: Velile Tinto & Associates Inc | F58: 827965.99 | G58: 827965.99 | H58: 56 | I58: 0 | J58: late | K58: Deceased | L58: 54-59 | Q58: 0.2664477 | R58: 0.2664477 | S58: 0.2664477 | T58: 9.98 | U58: 9.99 | V58: 827770.09 | W58: 507694.14 | X58: =W58/V58 -> 0.61332748
A59: 46250 | B59: 5022008031 | C59: Legal | D59: Charge_off_process | E59: Vezi & De Beer | F59: 189475.77 | G59: 189406.77 | H59: 43 | I59: 0 | J59: late | K59: Deceased | L59: 42-47 | Q59: 0.44153832 | R59: 0.44153832 | S59: 0.44153832 | T59: 0.57399981 | U59: 9.99 | V59: 189351.6 | W59: 55648.685 | X59: =W59/V59 -> 0.29389076
A60: 46250 | B60: 5052040169 | C60: Legal | D60: Deceased | E60: Internal | F60: 255209.26 | G60: 255140.26 | H60: 60 | I60: 0 | J60: late | K60: Deceased | L60: 60-65 | Q60: 0.20490322 | R60: 0.20490322 | S60: 0.25 | T60: 0.325 | U60: 9.99 | V60: 256256.67 | W60: 159182.6 | X60: =W60/V60 -> 0.62118423
A61: 46250 | B61: 5092050485 | C61: Legal | D61: Deceased | E61: EG Cooper Majiedt Inc | F61: 615275.47 | G61: 615269.72 | H61: 103 | I61: 1 | J61: late | K61: Deceased | L61: 72+ | Q61: 0.11948512 | R61: 0.11948512 | S61: 0.25 | T61: 0.3125 | U61: 9.99 | V61: 615269.72 | W61: 615269.72 | X61: =W61/V61 -> 1
A62: 46250 | B62: 6072053891 | C62: Legal | E62: Smit Sewgoolam | F62: 0 | G62: 0 | H62: 53 | I62: 0 | J62: late | K62: Litigation | L62: 48-53 | O62: 1 | Q62: 0.31442722 | R62: 0.31442722 | S62: 0.31442722 | T62: 0.40875538 | U62: 9.99 | X62: =W62/V62 -> #DIV/0!
A63: 46250 | B63: 6082003000 | C63: Legal | F63: 0 | G63: 0 | H63: 41 | I63: 0 | J63: late | K63: Litigation | L63: 36-41 | O63: 1 | X63: =W63/V63 -> #DIV/0!
A64: 46250 | B64: 6092059489 | C64: Legal | D64: Account in Legal Sales In Execution Proc | E64: Velile Tinto & Associates Inc | F64: 183853.82 | G64: 183853.82 | H64: 61 | I64: 0 | J64: late | K64: Deceased | L64: 60-65 | Q64: 0.40188126 | R64: 0.40188126 | S64: 0.40188126 | T64: 0.52244564 | U64: 9.99 | V64: 184286.26 | W64: 35856.665 | X64: =W64/V64 -> 0.19457047
A65: 46250 | B65: 6092063826 | C65: Legal | D65: Deceased | E65: Velile Tinto & Associates Inc | F65: 262644.92 | G65: 262644.92 | H65: 57 | I65: 0 | J65: late | K65: Deceased | L65: 54-59 | Q65: 0.29507588 | R65: 0.29507588 | S65: 0.29507588 | T65: 0.38359864 | U65: 0.38359864 | V65: 262568.26 | W65: 156869.89 | X65: =W65/V65 -> 0.59744421
A66: 46250 | B66: 7092072341 | C66: Legal | F66: 0 | G66: 0 | H66: 118 | I66: 1 | J66: late | K66: Litigation | L66: 72+ | O66: 1 | X66: =W66/V66 -> #DIV/0!
A67: 46250 | B67: 7092074778 | C67: Legal | D67: Deceased | E67: Internal | F67: 1225877.3 | G67: 749095.63 | H67: 91 | I67: 1 | J67: late | K67: Deceased | L67: 72+ | Q67: 0.039317367 | R67: 0.1 | S67: 0.25 | T67: 0.3125 | U67: 0.3125 | V67: 1225877.3 | W67: 1225877.3 | X67: =W67/V67 -> 1
A68: 46250 | B68: 8011026601 | C68: Legal | D68: Arms | F68: 0 | G68: 0 | H68: 118 | I68: 1 | J68: late | K68: Litigation | L68: 72+ | N68: 1 | O68: 1 | X68: =W68/V68 -> #DIV/0!
A69: 46250 | B69: 8011661493 | C69: Legal | D69: Account in Legal Sales In Execution Proc | E69: Strauss Daly Inc | F69: 379678.67 | G69: 379609.67 | H69: 98 | I69: 1 | J69: late | K69: Litigation | L69: 72+ | Q69: 0.11963324 | R69: 0.11963324 | S69: 0.25 | T69: 0.325 | U69: 9.99 | V69: 379609.67 | W69: 379609.67 | X69: =W69/V69 -> 1
A70: 46250 | B70: 8011866544 | C70: Legal | D70: Deceased | E70: Vezi & De Beer | F70: 240579.82 | G70: 240510.82 | H70: 52 | I70: 0 | J70: late | K70: Deceased | L70: 48-53 | Q70: 0.31935476 | R70: 0.31935476 | S70: 0.31935476 | T70: 0.41516119 | U70: 0.41516119 | V70: 241311.45 | W70: 141018.58 | X70: =W70/V70 -> 0.58438413
A71: 46250 | B71: 8011923017 | C71: Legal | D71: Deceased | E71: Vezi & De Beer | F71: 642565.24 | G71: 470344.62 | H71: 75 | I71: 1 | J71: late | K71: Deceased | L71: 72+ | Q71: 0.22547368 | R71: 0.22547368 | S71: 0.25 | T71: 0.325 | U71: 9.99 | V71: 644598.56 | W71: 644598.56 | X71: =W71/V71 -> 1
A72: 46250 | B72: 8017334280 | C72: Legal | D72: Small Balances between R100 and R200 | E72: Internal | F72: 161996.84 | G72: 85666.7 | H72: 40 | I72: 0 | J72: late | K72: Litigation | L72: 36-41 | Q72: 0.57238703 | R72: 0.57238703 | S72: 0.57238703 | T72: 0.74410314 | U72: 0.74410314 | V72: 161881.67 | W72: 40310.697 | X72: =W72/V72 -> 0.24901335
A73: 46250 | B73: 8018000046 | C73: Legal | D73: Summary Judgement Process | E73: Smit Sewgoolam | F73: 222282.45 | G73: 222276.7 | H73: 113 | I73: 1 | J73: late | K73: Deceased | L73: 72+ | M73: 1 | Q73: 0.069997869 | R73: 0.1 | S73: 0.25 | T73: 0.325 | U73: 0.325 | V73: 222212.78 | W73: 222212.78 | X73: =W73/V73 -> 1
A74: 46250 | B74: 8018977762 | C74: Legal | D74: Deceased | E74: Velile Tinto & Associates Inc | F74: 571719.13 | G74: 571713.38 | H74: 59 | I74: 0 | J74: late | K74: Deceased | L74: 54-59 | Q74: 0.28561154 | R74: 0.28561154 | S74: 0.28561154 | T74: 0.371295 | U74: 0.371295 | V74: 571567.31 | W74: 343724.91 | X74: =W74/V74 -> 0.60137259
A75: 46250 | B75: 8019748164 | C75: Legal | D75: Deceased | E75: Kemp and Associates | F75: 270513.67 | G75: 190872.14 | H75: 55 | I75: 0 | J75: late | K75: Deceased | L75: 54-59 | Q75: 0.29981385 | R75: 0.29981385 | S75: 0.29981385 | T75: 0.38975801 | U75: 0.38975801 | V75: 270432.24 | W75: 164347.99 | X75: =W75/V75 -> 0.60772337
A76: 46250 | B76: 8019754723 | C76: Legal | D76: Charge_off_process | E76: Smit Sewgoolam | F76: 154811.43 | G76: 154805.68 | H76: 64 | I76: 0 | J76: late | K76: Deceased | L76: 60-65 | Q76: 0.25755548 | R76: 0.25755548 | S76: 0.25755548 | T76: 0.33482213 | U76: 9.99 | V76: 154805.68 | W76: 97379.118 | X76: =W76/V76 -> 0.62904099
A77: 46250 | B77: 8019929061 | C77: Legal | D77: Charge_off_process | E77: Strauss Daly Inc | F77: 408711.11 | G77: 408705.36 | H77: 100 | I77: 1 | J77: late | K77: Deceased | L77: 72+ | Q77: 0.029011284 | R77: 0.1 | S77: 0.25 | T77: 0.3125 | U77: 9.99 | V77: 408705.36 | W77: 408705.36 | X77: =W77/V77 -> 1
A78: 46250 | B78: 8020311902 | C78: Legal | E78: K Gcolotele and Peter | F78: 0 | G78: -1257.83 | H78: 47 | I78: 0 | J78: late | K78: Litigation | L78: 42-47 | O78: 1 | X78: =W78/V78 -> #DIV/0!
A79: 46250 | B79: 8024111300 | C79: Legal | D79: Small Balances between R100 and R200 | E79: Internal | F79: 139934.6 | G79: 139865.6 | H79: 37 | I79: 0 | J79: late | K79: Litigation | L79: 36-41 | Q79: 0.56588414 | R79: 0.56588414 | S79: 0.56588414 | T79: 0.73564938 | U79: 0.73564938 | V79: 139865.6 | W79: 39827.069 | X79: =W79/V79 -> 0.28475242
A80: 46250 | B80: 8024345072 | C80: Legal | D80: Deceased | E80: Velile Tinto & Associates Inc | F80: 253885.21 | G80: 249055.33 | H80: 45 | I80: 0 | J80: late | K80: Deceased | L80: 42-47 | Q80: 0.35405716 | R80: 0.35405716 | S80: 0.35405716 | T80: 0.4602743 | U80: 0.4602743 | V80: 248988.68 | W80: 69248.699 | X80: =W80/V80 -> 0.27811987
A81: 46250 | B81: 8025238149 | C81: Legal | D81: Charge_off_process | E81: Glover | F81: 354432.53 | G81: 166505.89 | H81: 49 | I81: 0 | J81: late | K81: Deceased | L81: 48-53 | Q81: 0.32958864 | R81: 0.32958864 | S81: 0.32958864 | T81: 0.42846523 | U81: 9.99 | V81: 353889.35 | W81: 107223.37 | X81: =W81/V81 -> 0.30298557
A82: 46250 | B82: 8027088053 | C82: Legal | D82: Account in Legal Sales In Execution Proc | E82: Strauss Daly Inc | F82: 835571.71 | G82: 572699.85 | H82: 79 | I82: 1 | J82: late | K82: Litigation | L82: 72+ | Q82: 0.26118035 | R82: 0.26118035 | S82: 0.26118035 | T82: 0.26118035 | U82: 9.99 | V82: 835571.71 | W82: 835571.71 | X82: =W82/V82 -> 1
A83: 46250 | B83: 8027127784 | C83: Legal | D83: Charge_off_process | E83: Kemp and Associates | F83: 604604.59 | G83: 604604.59 | H83: 73 | I83: 1 | J83: late | K83: Deceased | L83: 72+ | Q83: 0.22080535 | R83: 0.22080535 | S83: 0.25 | T83: 0.3 | U83: 0.3 | V83: 606149.02 | W83: 394306.44 | X83: =W83/V83 -> 0.65051073
A84: 46250 | B84: 8028489684 | C84: Legal | D84: Charge_off_process | E84: Kemp and Associates | F84: 258230.29 | G84: 252522.33 | H84: 63 | I84: 0 | J84: late | K84: Deceased | L84: 60-65 | Q84: 0.26211456 | R84: 0.26211456 | S84: 0.26211456 | T84: 0.34074893 | U84: 0.34074893 | V84: 252453.73 | W84: 158307.88 | X84: =W84/V84 -> 0.6270768
A85: 46250 | B85: 8029702122 | C85: Legal | D85: Deceased | E85: Velile Tinto & Associates Inc | F85: 651447.86 | G85: 651447.86 | H85: 71 | I85: 0 | J85: late | K85: Deceased | L85: 65-71 | Q85: 0.11067657 | R85: 0.11067657 | S85: 0.25 | T85: 0.3125 | U85: 0.3125 | V85: 651447.86 | W85: 651447.86 | X85: =W85/V85 -> 1
A86: 46250 | B86: 8029722152 | C86: Legal | D86: Account in Legal Sales In Execution Proc | E86: Poswa Inc | F86: 1475780.8 | G86: 1475711.8 | H86: 95 | I86: 1 | J86: late | K86: Litigation | L86: 72+ | Q86: 0.13014205 | R86: 0.13014205 | S86: 0.25 | T86: 0.25 | U86: 0.25 | V86: 1473016.8 | W86: 1473016.8 | X86: =W86/V86 -> 1
A87: 46250 | B87: 8029852250 | C87: Legal | D87: Deceased | E87: Kemp and Associates | F87: 458419.24 | G87: 458419.24 | H87: 112 | I87: 1 | J87: late | K87: Deceased | L87: 72+ | Q87: 0.020371631 | R87: 0.1 | S87: 0.25 | T87: 0.25 | U87: 0.25 | V87: 458419.24 | W87: 458419.24 | X87: =W87/V87 -> 1
A88: 46250 | B88: 8031754129 | C88: Legal | D88: Deceased | E88: Internal | F88: 165636.05 | G88: 165567.05 | H88: 63 | I88: 0 | J88: late | K88: Deceased | L88: 60-65 | Q88: 0.26211456 | R88: 0.26211456 | S88: 0.26211456 | T88: 0.34074893 | U88: 9.99 | V88: 165567.05 | W88: 103823.26 | X88: =W88/V88 -> 0.6270768
A89: 46250 | B89: 8033969071 | C89: Legal | D89: Charge_off_process | E89: Edelstein Faber Grobbler Inc | F89: -2705.07 | G89: -132997.21 | H89: 122 | I89: 1 | J89: late | K89: Litigation | L89: 72+ | P89: 1 | X89: =W89/V89 -> #DIV/0!
A90: 46250 | B90: 8035320148 | C90: Legal | D90: Deceased | E90: Sandenberg Nel Haggard | F90: 262284.23 | G90: 262284.23 | H90: 146 | I90: 1 | J90: late | K90: Deceased | L90: 72+ | Q90: 0.007392789 | R90: 0.1 | S90: 0.25 | T90: 0.3125 | U90: 0.3125 | V90: 262284.23 | W90: 262284.23 | X90: =W90/V90 -> 1
A91: 46250 | B91: 8040016259 | C91: Legal | D91: Charge_off_process | E91: Sandenberg Nel Haggard | F91: 293407.93 | G91: 293338.93 | H91: 61 | I91: 0 | J91: late | K91: Litigation | L91: 60-65 | Q91: 0.37439618 | R91: 0.37439618 | S91: 0.37439618 | T91: 0.48671503 | U91: 9.99 | V91: 292960.24 | W91: 177329.12 | X91: =W91/V91 -> 0.60530097
A92: 46250 | B92: 8040094316 | C92: Legal | D92: Small Balances between R100 and R200 | E92: Internal | F92: 182267.2 | G92: 182198.2 | H92: 56 | I92: 0 | J92: late | K92: Litigation | L92: 54-59 | Q92: 0.39836643 | R92: 0.39836643 | S92: 0.39836643 | T92: 0.51787636 | U92: 0.51787636 | V92: 182152.64 | W92: 108468.26 | X92: =W92/V92 -> 0.59548003
A93: 46250 | B93: 8040126521 | C93: Legal | D93: Deceased | E93: Kemp and Associates | F93: 291035.91 | G93: 290966.91 | H93: 97 | I93: 1 | J93: late | K93: Deceased | L93: 72+ | Q93: 0.031675308 | R93: 0.1 | S93: 0.25 | T93: 0.325 | U93: 9.99 | V93: 291478.44 | W93: 291478.44 | X93: =W93/V93 -> 1
A94: 46250 | B94: 8040147670 | C94: Legal | D94: Charge_off_process | E94: Kemp and Associates | F94: 332311.94 | G94: 332306.19 | H94: 122 | I94: 1 | J94: late | K94: Deceased | L94: 72+ | Q94: 0.015141927 | R94: 0.1 | S94: 0.25 | T94: 0.325 | U94: 0.325 | V94: 332306.19 | W94: 332306.19 | X94: =W94/V94 -> 1
A95: 46250 | B95: 8040563191 | C95: Legal | D95: Charge_off_process | E95: Kemp and Associates | F95: 650203.87 | G95: 634230.53 | H95: 76 | I95: 1 | J95: late | K95: Deceased | L95: 72+ | Q95: 0.30832901 | R95: 0.30832901 | S95: 0.30832901 | T95: 0.40082772 | U95: 9.99 | V95: 653882.32 | W95: 653882.32 | X95: =W95/V95 -> 1
A96: 46250 | B96: 8040568086 | C96: Legal | D96: Account in Legal Sales In Execution Proc | E96: Strauss Daly Inc | F96: 307427.76 | G96: 307358.76 | H96: 41 | I96: 0 | J96: late | K96: Litigation | L96: 36-41 | Q96: 0.49915523 | R96: 0.49915523 | S96: 0.49915523 | T96: 0.64890181 | U96: 0.64890181 | V96: 307275.26 | W96: 142686.38 | X96: =W96/V96 -> 0.46436012
A97: 46250 | B97: 8040686977 | C97: Legal | D97: Charge_off_process | E97: Strauss Daly Inc | F97: 326466.18 | G97: 301111.79 | H97: 69 | I97: 0 | J97: late | K97: Litigation | L97: 65-71 | Q97: 0.33651435 | R97: 0.33651435 | S97: 0.33651435 | T97: 0.43746865 | U97: 9.99 | V97: 326306.31 | W97: 202640.94 | X97: =W97/V97 -> 0.62101447
A98: 46250 | B98: 8040695699 | C98: Legal | D98: Deceased | E98: Velile Tinto & Associates Inc | F98: 465339.52 | G98: 465339.52 | H98: 75 | I98: 1 | J98: late | K98: Deceased | L98: 72+ | Q98: 0.21363411 | R98: 0.21363411 | S98: 0.25 | T98: 0.325 | U98: 9.99 | V98: 465339.52 | W98: 465339.52 | X98: =W98/V98 -> 1
A99: 46250 | B99: 8040721696 | C99: Legal | D99: Charge_off_process | E99: Kemp and Associates | F99: 1310378.5 | G99: 1310378.5 | H99: 130 | I99: 1 | J99: late | K99: Deceased | L99: 72+ | Q99: 0.011930793 | R99: 0.1 | S99: 0.25 | T99: 0.25 | U99: 0.25 | V99: 1310378.5 | W99: 1310378.5 | X99: =W99/V99 -> 1
A100: 46250 | B100: 8040737962 | C100: Legal | D100: Deceased | E100: Velile Tinto & Associates Inc | F100: 542821.87 | G100: 336007.95 | H100: 79 | I100: 1 | J100: late | K100: Deceased | L100: 72+ | Q100: 0.19704755 | R100: 0.19704755 | S100: 0.25 | T100: 0.325 | U100: 0.325 | V100: 542675.97 | W100: 542675.97 | X100: =W100/V100 -> 1
...

Sheet Sheet2
A1: account_number | B1: CUSTOMER_TYPE_CODE | C1: CUSTOMER_TYPE
A2: 8086054891
A3: 51990811
A4: 8085984643
A5: 8088795007
A6: 8059449502
A7: 8076075772
A8: 8064161793
A9: 8093724833
A10: 8072508246
A11: 8076086242
A12: 8071215692
A13: 8081065544
... A1981: 8069363574
A1982: 8069379557 | B1982: 1 | C1982: Private individuals
A1983: 8093785007 | B1983: 1 | C1983: Private individuals
A1984: 8080548503 | B1984: 1 | C1984: Private individuals
A1985: 8069380726 | B1985: 1 | C1985: Private individuals
A1986: 8086088878 | B1986: 1 | C1986: Private individuals
A1987: 8094062995 | B1987: 1 | C1987: Private individuals
A1988: 8094379190 | B1988: 1 | C1988: Private individuals
A1989: 8094340456 | B1989: 1 | C1989: Private individuals
A1990: 8080684765 | B1990: 1 | C1990: Private individuals
A1991: 8094297508 | B1991: 1 | C1991: Private individuals
A1992: 8094249296 | B1992: 1 | C1992: Private individuals
A1993: 8080388802 | B1993: 1 | C1993: Private individuals
... A17462: 8064259457 | B17462: 84 | C17462: Farmers

Sheet deceased
A1: information_date | B1: account_number | C1: pool2 | D1: pool | E1: attorney_name | F1: current_liability | G1: arrears_amount | H1: MIL | I1: mil_72 | J1: legal_ind | K1: Legal_Category | L1: MIL_BUCK | M1: customer_type | N1: settlement_minimum | O1: settlement_maximum | P1: coverage | Q1: expected_recovery_based_on_minimum_settlement
A2: 46250 | B2: 50595358 | C2: Legal | D2: Deceased | E2: Velile Tinto & Associates Inc | F2: 315036.98 | G2: 315031.23 | H2: 133 | I2: 1 | J2: late | K2: Deceased | L2: 72+ | M2: =VLOOKUP(B2,Sheet2!A:C,3,FALSE) -> Joint and several accounts | N2: 0.1 | O2: 0.25 | P2: 1 | Q2: =F2*N2 -> 31503.698
A3: 46250 | B3: 50988325 | C3: Legal | D3: Charge_off_process | E3: Kemp and Associates | F3: 351037.43 | G3: 351037.43 | H3: 113 | I3: 1 | J3: late | K3: Deceased | L3: 72+ | M3: =VLOOKUP(B3,Sheet2!A:C,3,FALSE) -> Joint and several accounts | N3: 0.1 | O3: 0.25 | P3: 1 | Q3: =F3*N3 -> 35103.743
A4: 46250 | B4: 52281989 | C4: Legal | D4: Deceased | E4: Velile Tinto & Associates Inc | F4: 924540.41 | G4: 924471.41 | H4: 107 | I4: 1 | J4: late | K4: Deceased | L4: 72+ | M4: =VLOOKUP(B4,Sheet2!A:C,3,FALSE) -> Private individuals | N4: 0.1 | O4: 0.25 | P4: 1 | Q4: =F4*N4 -> 92454.041
A5: 46250 | B5: 52751306 | C5: Legal | D5: Deceased | E5: Velile Tinto & Associates Inc | F5: 330686.96 | G5: 330686.96 | H5: 103 | I5: 1 | J5: late | K5: Deceased | L5: 72+ | M5: =VLOOKUP(B5,Sheet2!A:C,3,FALSE) -> Joint and several accounts | N5: 0.1 | O5: 0.25 | P5: 1 | Q5: =F5*N5 -> 33068.696
A6: 46250 | B6: 54967063 | C6: Legal | D6: Deceased | E6: Vezi & De Beer | F6: 180567.78 | G6: 180562.03 | H6: 82 | I6: 1 | J6: late | K6: Deceased | L6: 72+ | M6: =VLOOKUP(B6,Sheet2!A:C,3,FALSE) -> Private individuals | N6: 0.17959562 | O6: 0.25 | P6: 1 | Q6: =F6*N6 -> 32429.183
A7: 46250 | B7: 55708118 | C7: Legal | D7: Charge_off_process | E7: Strauss Daly Inc | F7: 562493.96 | G7: 562488.21 | H7: 130 | I7: 1 | J7: late | K7: Deceased | L7: 72+ | M7: =VLOOKUP(B7,Sheet2!A:C,3,FALSE) -> Joint and several accounts | N7: 0.1 | O7: 0.25 | P7: 1 | Q7: =F7*N7 -> 56249.396
A8: 46250 | B8: 56408797 | C8: Legal | D8: Deceased | E8: Velile Tinto & Associates Inc | F8: 616702.73 | G8: 616702.73 | H8: 89 | I8: 1 | J8: late | K8: Deceased | L8: 72+ | M8: =VLOOKUP(B8,Sheet2!A:C,3,FALSE) -> Private individuals | N8: 0.1 | O8: 0.25 | P8: 1 | Q8: =F8*N8 -> 61670.273
A9: 46250 | B9: 56474757 | C9: Legal | D9: Deceased | E9: Velile Tinto & Associates Inc | F9: 364838.41 | G9: 364838.41 | H9: 121 | I9: 1 | J9: late | K9: Deceased | L9: 72+ | M9: =VLOOKUP(B9,Sheet2!A:C,3,FALSE) -> Private individuals | N9: 0.1 | O9: 0.25 | P9: 1 | Q9: =F9*N9 -> 36483.841
A10: 46250 | B10: 56706372 | C10: Legal | D10: Charge_off_process | E10: Velile Tinto & Associates Inc | F10: 70375.3 | G10: 53037.15 | H10: 101 | I10: 1 | J10: late | K10: Deceased | L10: 72+ | M10: =VLOOKUP(B10,Sheet2!A:C,3,FALSE) -> Joint and several accounts | N10: 0.1 | O10: 0.25 | P10: 1 | Q10: =F10*N10 -> 7037.53
A11: 46250 | B11: 57182261 | C11: Legal | D11: Deceased | E11: Kemp and Associates | F11: 254495.1 | G11: 254489.35 | H11: 77 | I11: 1 | J11: late | K11: Deceased | L11: 72+ | M11: =VLOOKUP(B11,Sheet2!A:C,3,FALSE) -> Joint and several accounts | N11: 0.20528726 | O11: 0.25 | P11: 1 | Q11: =F11*N11 -> 52244.602
A12: 46250 | B12: 58191736 | C12: Legal | D12: Charge_off_process | E12: Strauss Daly Inc | F12: 370761.58 | G12: 370692.58 | H12: 72 | I12: 1 | J12: late | K12: Deceased | L12: 72+ | M12: =VLOOKUP(B12,Sheet2!A:C,3,FALSE) -> Private individuals | N12: 0.10678774 | O12: 0.25 | P12: 1 | Q12: =F12*N12 -> 39592.792
A13: 46250 | B13: 58646237 | C13: Legal | D13: Deceased | E13: Sandenberg Nel Haggard | F13: 179426.3 | G13: 174109.57 | H13: 101 | I13: 1 | J13: late | K13: Deceased | L13: 72+ | M13: =VLOOKUP(B13,Sheet2!A:C,3,FALSE) -> Private individuals | N13: 0.1 | O13: 0.25 | P13: 1 | Q13: =F13*N13 -> 17942.63
... A32: 46250 | B32: 8042144373 | C32: Legal | D32: Deceased | E32: Sandenberg Nel Haggard | F32: 253666.12 | G32: 253660.37 | H32: 105 | I32: 1 | J32: late | K32: Deceased | L32: 72+ | M32: =VLOOKUP(B32,Sheet2!A:C,3,FALSE) -> Private individuals | N32: 0.1 | O32: 0.25 | P32: 1 | Q32: =F32*N32 -> 25366.612
A33: 46250 | B33: 8042827751 | C33: Legal | D33: Deceased | F33: 464788.89 | G33: 464788.89 | H33: 107 | I33: 1 | J33: late | K33: Deceased | L33: 72+ | M33: =VLOOKUP(B33,Sheet2!A:C,3,FALSE) -> Private individuals | N33: 0.1 | O33: 0.25 | P33: 1 | Q33: =F33*N33 -> 46478.889
A34: 46250 | B34: 8043014064 | C34: Legal | D34: Deceased | E34: Vezi & De Beer | F34: 390092.68 | G34: 258852.48 | H34: 77 | I34: 1 | J34: late | K34: Deceased | L34: 72+ | M34: =VLOOKUP(B34,Sheet2!A:C,3,FALSE) -> Joint and several accounts | N34: 0.20399151 | O34: 0.25 | P34: 1 | Q34: =F34*N34 -> 79575.595
A35: 46250 | B35: 8043095064 | C35: Legal | D35: Charge_off_process | E35: Strauss Daly Inc | F35: 458942.48 | G35: 290374.59 | H35: 75 | I35: 1 | J35: late | K35: Deceased | L35: 72+ | M35: =VLOOKUP(B35,Sheet2!A:C,3,FALSE) -> Joint and several accounts | N35: 0.21363411 | O35: 0.25 | P35: 1 | Q35: =F35*N35 -> 98045.77
A36: 46250 | B36: 8044107761 | C36: Legal | D36: Deceased | E36: Sandenberg Nel Haggard | F36: 559613.09 | G36: 559613.09 | H36: 79 | I36: 1 | J36: late | K36: Deceased | L36: 72+ | M36: =VLOOKUP(B36,Sheet2!A:C,3,FALSE) -> Joint and several accounts | N36: 0.19423835 | O36: 0.25 | P36: 1 | Q36: =F36*N36 -> 108698.32
A37: 46250 | B37: 8044259841 | C37: Legal | D37: Deceased | E37: Velile Tinto & Associates Inc | F37: 762279.08 | G37: 762279.08 | H37: 80 | I37: 1 | J37: late | K37: Deceased | L37: 72+ | M37: =VLOOKUP(B37,Sheet2!A:C,3,FALSE) -> Private individuals | N37: 0.18064314 | O37: 0.25 | P37: 1 | Q37: =F37*N37 -> 137700.49
A38: 46250 | B38: 8044443927 | C38: Legal | D38: Charge_off_process | E38: Kemp and Associates | F38: 560906.91 | G38: 560901.16 | H38: 100 | I38: 1 | J38: late | K38: Deceased | L38: 72+ | M38: =VLOOKUP(B38,Sheet2!A:C,3,FALSE) -> Joint and several accounts | N38: 0.1 | O38: 0.25 | P38: 1 | Q38: =F38*N38 -> 56090.691
A39: 46250 | B39: 8044708476 | C39: Legal | D39: Deceased | E39: Vezi & De Beer | F39: 420255.12 | G39: 420186.12 | H39: 120 | I39: 1 | J39: late | K39: Deceased | L39: 72+ | M39: =VLOOKUP(B39,Sheet2!A:C,3,FALSE) -> Private individuals | N39: 0.1 | O39: 0.25 | P39: 1 | Q39: =F39*N39 -> 42025.512
A40: 46250 | B40: 8045126801 | C40: Legal | D40: Deceased | E40: Internal | F40: 390714.36 | G40: 348581.3 | H40: 87 | I40: 1 | J40: late | K40: Deceased | L40: 72+ | M40: =VLOOKUP(B40,Sheet2!A:C,3,FALSE) -> Joint and several accounts | N40: 0.1 | O40: 0.25 | P40: 1 | Q40: =F40*N40 -> 39071.436
A41: 46250 | B41: 8045140322 | C41: Legal | D41: Charge_off_process | E41: Strauss Daly Inc | F41: 208395.82 | G41: 208390.07 | H41: 74 | I41: 1 | J41: late | K41: Deceased | L41: 72+ | M41: =VLOOKUP(B41,Sheet2!A:C,3,FALSE) -> Joint and several accounts | N41: 0.21131254 | O41: 0.25 | P41: 1 | Q41: =F41*N41 -> 44036.65
A42: 46250 | B42: 8045154361 | C42: Legal | D42: Deceased | E42: Kemp and Associates | F42: 389260.18 | G42: 389260.18 | H42: 78 | I42: 1 | J42: late | K42: Deceased | L42: 72+ | M42: =VLOOKUP(B42,Sheet2!A:C,3,FALSE) -> Joint and several accounts | N42: 0.19985631 | O42: 0.25 | P42: 1 | Q42: =F42*N42 -> 77796.103
A43: 46250 | B43: 8045218307 | C43: Legal | D43: Charge_off_process | E43: Glover | F43: 938156.9 | G43: 673115.66 | H43: 105 | I43: 1 | J43: late | K43: Deceased | L43: 72+ | M43: =VLOOKUP(B43,Sheet2!A:C,3,FALSE) -> Joint and several accounts | N43: 0.1 | O43: 0.25 | P43: 1 | Q43: =F43*N43 -> 93815.69
A44: 46250 | B44: 8045386099 | C44: Legal | D44: Deceased | E44: Vezi & De Beer | F44: 421007.17 | G44: 309815.48 | H44: 77 | I44: 1 | J44: late | K44: Deceased | L44: 72+ | M44: =VLOOKUP(B44,Sheet2!A:C,3,FALSE) -> Private individuals | N44: 0.20004385 | O44: 0.25 | P44: 1 | Q44: =F44*N44 -> 84219.896
A45: 46250 | B45: 8046429343 | C45: Legal | D45: Deceased | E45: Velile Tinto & Associates Inc | F45: 190896.7 | G45: 190890.95 | H45: 115 | I45: 1 | J45: late | K45: Deceased | L45: 72+ | M45: =VLOOKUP(B45,Sheet2!A:C,3,FALSE) -> Joint and several accounts | N45: 0.1 | O45: 0.25 | P45: 1 | Q45: =F45*N45 -> 19089.67
... A149: 46250 | B149: 8064677093 | C149: Legal | D149: Deceased | E149: Vezi & De Beer | F149: 2048674.9 | G149: 2048605.9 | H149: 110 | I149: 1 | J149: late | K149: Deceased | L149: 72+ | M149: =VLOOKUP(B149,Sheet2!A:C,3,FALSE) -> Joint and several accounts | N149: 0.1 | O149: 0.25 | P149: 1 | Q149: =F149*N149 -> 204867.49
A150: 46250 | B150: 8064741723 | C150: Legal | D150: Deceased | F150: 1733339.6 | G150: 1733270.6 | H150: 119 | I150: 1 | J150: late | K150: Deceased | L150: 72+ | M150: =VLOOKUP(B150,Sheet2!A:C,3,FALSE) -> Private individuals | N150: 0.1 | O150: 0.25 | P150: 1 | Q150: =F150*N150 -> 173333.96
A151: 46250 | B151: 8064774827 | C151: Legal | D151: Charge_off_process | E151: Vezi & De Beer | F151: 285606.97 | G151: 285606.97 | H151: 121 | I151: 1 | J151: late | K151: Deceased | L151: 72+ | M151: =VLOOKUP(B151,Sheet2!A:C,3,FALSE) -> Joint and several accounts | N151: 0.1 | O151: 0.25 | P151: 1 | Q151: =F151*N151 -> 28560.697
A152: 46250 | B152: 8064854857 | C152: Legal | D152: Deceased | E152: Velile Tinto & Associates Inc | F152: 186101.2 | G152: 186095.45 | H152: 130 | I152: 1 | J152: late | K152: Deceased | L152: 72+ | M152: =VLOOKUP(B152,Sheet2!A:C,3,FALSE) -> Private individuals | N152: 0.1 | O152: 0.25 | P152: 1 | Q152: =F152*N152 -> 18610.12
A153: 46250 | B153: 8064932550 | C153: Legal | D153: Deceased | E153: Velile Tinto & Associates Inc | F153: 2900758.1 | G153: 2900689.1 | H153: 99 | I153: 1 | J153: late | K153: Deceased | L153: 72+ | M153: =VLOOKUP(B153,Sheet2!A:C,3,FALSE) -> Joint and several accounts | N153: 0.1 | O153: 0.25 | P153: 1 | Q153: =F153*N153 -> 290075.81
A154: 46250 | B154: 8064974342 | C154: Legal | D154: Deceased | E154: Velile Tinto & Associates Inc | F154: 886664.76 | G154: 886659.01 | H154: 126 | I154: 1 | J154: late | K154: Deceased | L154: 72+ | M154: =VLOOKUP(B154,Sheet2!A:C,3,FALSE) -> Joint and several accounts | N154: 0.1 | O154: 0.25 | P154: 1 | Q154: =F154*N154 -> 88666.476
A155: 46250 | B155: 8065090907 | C155: Legal | D155: Deceased | E155: Velile Tinto & Associates Inc | F155: 1847757.8 | G155: 1847688.8 | H155: 122 | I155: 1 | J155: late | K155: Deceased | L155: 72+ | M155: =VLOOKUP(B155,Sheet2!A:C,3,FALSE) -> Joint and several accounts | N155: 0.1 | O155: 0.25 | P155: 1 | Q155: =F155*N155 -> 184775.78
A156: 46250 | B156: 8065108625 | C156: Legal | D156: Charge_off_process | E156: Kemp and Associates | F156: 293956.18 | G156: 247437.96 | H156: 91 | I156: 1 | J156: late | K156: Deceased | L156: 72+ | M156: =VLOOKUP(B156,Sheet2!A:C,3,FALSE) -> Private individuals | N156: 0.1 | O156: 0.25 | P156: 1 | Q156: =F156*N156 -> 29395.618
A157: 46250 | B157: 8065277737 | C157: Legal | D157: Deceased | E157: Velile Tinto & Associates Inc | F157: 629991.63 | G157: 629985.88 | H157: 101 | I157: 1 | J157: late | K157: Deceased | L157: 72+ | M157: =VLOOKUP(B157,Sheet2!A:C,3,FALSE) -> Joint and several accounts | N157: 0.1 | O157: 0.25 | P157: 1 | Q157: =F157*N157 -> 62999.163
A158: 46250 | B158: 8065293690 | C158: Legal | D158: Charge_off_process | E158: EG Cooper Majiedt Inc | F158: 234414.56 | G158: 234408.81 | H158: 120 | I158: 1 | J158: late | K158: Deceased | L158: 72+ | M158: =VLOOKUP(B158,Sheet2!A:C,3,FALSE) -> Sole Proprietor | N158: 0.1 | O158: 0.25 | P158: 1 | Q158: =F158*N158 -> 23441.456
A159: 46250 | B159: 8065307039 | C159: Legal | D159: Deceased | E159: Kemp and Associates | F159: 820601.88 | G159: 566425.92 | H159: 130 | I159: 1 | J159: late | K159: Deceased | L159: 72+ | M159: =VLOOKUP(B159,Sheet2!A:C,3,FALSE) -> Private individuals | N159: 0.1 | O159: 0.25 | P159: 1 | Q159: =F159*N159 -> 82060.188
A160: 46250 | B160: 8065316109 | C160: Legal | D160: Charge_off_process | E160: Delberg Attorneys | F160: 934625.58 | G160: 934556.58 | H160: 114 | I160: 1 | J160: late | K160: Deceased | L160: 72+ | M160: =VLOOKUP(B160,Sheet2!A:C,3,FALSE) -> Private individuals | N160: 0.1 | O160: 0.25 | P160: 1 | Q160: =F160*N160 -> 93462.558
A161: 46250 | B161: 8065409106 | C161: Legal | D161: Deceased | E161: Sandenberg Nel Haggard | F161: 449576.95 | G161: 449576.95 | H161: 165 | I161: 1 | J161: late | K161: Deceased | L161: 72+ | M161: =VLOOKUP(B161,Sheet2!A:C,3,FALSE) -> Joint and several accounts | N161: 0.1 | O161: 0.25 | P161: 1 | Q161: =F161*N161 -> 44957.695
A162: 46250 | B162: 8065426659 | C162: Legal | D162: Charge_off_process | E162: Kemp and Associates | F162: 618103.13 | G162: 618103.13 | H162: 67 | I162: 0 | J162: late | K162: Deceased | L162: 65-71 | M162: =VLOOKUP(B162,Sheet2!A:C,3,FALSE) -> Joint and several accounts | N162: 0.12662368 | O162: 0.25 | P162: 1 | Q162: =F162*N162 -> 78266.494
... A178: 46250 | B178: 8065982019 | C178: Legal | D178: Charge_off_process | E178: Kemp and Associates | F178: 1267442.2 | G178: 1267373.2 | H178: 76 | I178: 1 | J178: late | K178: Deceased | L178: 72+ | M178: =VLOOKUP(B178,Sheet2!A:C,3,FALSE) -> Joint and several accounts | N178: 0.20944706 | O178: 0.25 | P178: 1 | Q178: =F178*N178 -> 265462.04
A179: 46250 | B179: 8066074338 | C179: Legal | D179: Deceased | F179: 944864.7 | G179: 944858.95 | H179: 93 | I179: 1 | J179: late | K179: Deceased | L179: 72+ | M179: =VLOOKUP(B179,Sheet2!A:C,3,FALSE) -> Private individuals | N179: 0.1 | O179: 0.25 | P179: 1 | Q179: =F179*N179 -> 94486.47
A180: 46250 | B180: 8066159384 | C180: Legal | D180: Deceased | E180: Velile Tinto & Associates Inc | F180: 608878.9 | G180: 608873.15 | H180: 102 | I180: 1 | J180: late | K180: Deceased | L180: 72+ | M180: =VLOOKUP(B180,Sheet2!A:C,3,FALSE) -> Private individuals | N180: 0.1 | O180: 0.25 | P180: 1 | Q180: =F180*N180 -> 60887.89
A181: 46250 | B181: 8066211645 | C181: Legal | D181: Charge_off_process | E181: Kemp and Associates | F181: 1057613.9 | G181: 672408.36 | H181: 87 | I181: 1 | J181: late | K181: Deceased | L181: 72+ | M181: =VLOOKUP(B181,Sheet2!A:C,3,FALSE) -> Private individuals | N181: 0.1 | O181: 0.25 | P181: 1 | Q181: =F181*N181 -> 105761.39
A182: 46250 | B182: 8066226795 | C182: Legal | D182: Charge_off_process | E182: Kemp and Associates | F182: 1263222.7 | G182: 1040083 | H182: 116 | I182: 1 | J182: late | K182: Deceased | L182: 72+ | M182: =VLOOKUP(B182,Sheet2!A:C,3,FALSE) -> Private individuals | N182: 0.1 | O182: 0.25 | P182: 1 | Q182: =F182*N182 -> 126322.27
A183: 46250 | B183: 8066252245 | C183: Legal | D183: Charge_off_process | E183: Vezi & De Beer | F183: 4319223.7 | G183: 1893741.3 | H183: 85 | I183: 1 | J183: late | K183: Deceased | L183: 72+ | M183: =VLOOKUP(B183,Sheet2!A:C,3,FALSE) -> Joint and several accounts | N183: 0.16649926 | O183: 0.25 | P183: 1 | Q183: =F183*N183 -> 719147.53
A184: 46250 | B184: 8066257677 | C184: Legal | D184: Charge_off_process | E184: Smit Sewgoolam | F184: 614180.22 | G184: 614174.47 | H184: 130 | I184: 1 | J184: late | K184: Deceased | L184: 72+ | M184: =VLOOKUP(B184,Sheet2!A:C,3,FALSE) -> Private individuals | N184: 0.1 | O184: 0.25 | P184: 1 | Q184: =F184*N184 -> 61418.022
A185: 46250 | B185: 8066291097 | C185: Legal | D185: Deceased | E185: EG Cooper Majiedt Inc | F185: 780290.11 | G185: 780284.36 | H185: 182 | I185: 1 | J185: late | K185: Deceased | L185: 72+ | M185: =VLOOKUP(B185,Sheet2!A:C,3,FALSE) -> Joint and several accounts | N185: 0.1 | O185: 0.25 | P185: 1 | Q185: =F185*N185 -> 78029.011
A186: 46250 | B186: 8066328650 | C186: Legal | D186: Charge_off_process | E186: Kemp and Associates | F186: 374768.09 | G186: 66825.06 | H186: 72 | I186: 1 | J186: late | K186: Deceased | L186: 72+ | M186: =VLOOKUP(B186,Sheet2!A:C,3,FALSE) -> Joint and several accounts | N186: 0.10678774 | O186: 0.25 | P186: 1 | Q186: =F186*N186 -> 40020.638
A187: 46250 | B187: 8066383739 | C187: Legal | D187: Deceased | E187: Velile Tinto & Associates Inc | F187: 471509.49 | G187: 471440.49 | H187: 115 | I187: 1 | J187: late | K187: Deceased | L187: 72+ | M187: =VLOOKUP(B187,Sheet2!A:C,3,FALSE) -> Joint and several accounts | N187: 0.1 | O187: 0.25 | P187: 1 | Q187: =F187*N187 -> 47150.949
A188: 46250 | B188: 8066387107 | C188: Legal | D188: Charge_off_process | E188: Velile Tinto & Associates Inc | F188: 682841.17 | G188: 682835.42 | H188: 119 | I188: 1 | J188: late | K188: Deceased | L188: 72+ | M188: =VLOOKUP(B188,Sheet2!A:C,3,FALSE) -> Joint and several accounts | N188: 0.1 | O188: 0.25 | P188: 1 | Q188: =F188*N188 -> 68284.117
A189: 46250 | B189: 8066433744 | C189: Legal | D189: Deceased | E189: Vezi & De Beer | F189: 1082233.7 | G189: 777750.3 | H189: 111 | I189: 1 | J189: late | K189: Deceased | L189: 72+ | M189: =VLOOKUP(B189,Sheet2!A:C,3,FALSE) -> Joint and several accounts | N189: 0.1 | O189: 0.25 | P189: 1 | Q189: =F189*N189 -> 108223.37
A190: 46250 | B190: 8066473097 | C190: Legal | D190: Deceased | F190: 1561230.3 | G190: 1561224.6 | H190: 86 | I190: 1 | J190: late | K190: Deceased | L190: 72+ | M190: =VLOOKUP(B190,Sheet2!A:C,3,FALSE) -> Joint and several accounts | N190: 0.1 | O190: 0.25 | P190: 1 | Q190: =F190*N190 -> 156123.03
A191: 46250 | B191: 8066493564 | C191: Legal | D191: Deceased | E191: Vezi & De Beer | F191: 327472.99 | G191: 327403.99 | H191: 105 | I191: 1 | J191: late | K191: Deceased | L191: 72+ | M191: =VLOOKUP(B191,Sheet2!A:C,3,FALSE) -> Joint and several accounts | N191: 0.1 | O191: 0.25 | P191: 1 | Q191: =F191*N191 -> 32747.299
A192: 46250 | B192: 8066509387 | C192: Legal | D192: Deceased | E192: Velile Tinto & Associates Inc | F192: 388698.3 | G192: 388629.3 | H192: 106 | I192: 1 | J192: late | K192: Deceased | L192: 72+ | M192: =VLOOKUP(B192,Sheet2!A:C,3,FALSE) -> Private individuals | N192: 0.1 | O192: 0.25 | P192: 1 | Q192: =F192*N192 -> 38869.83
A193: 46250 | B193: 8066646684 | C193: Legal | D193: Deceased | E193: Vezi & De Beer | F193: 2222108.7 | G193: 1524692.7 | H193: 112 | I193: 1 | J193: late | K193: Deceased | L193: 72+ | M193: =VLOOKUP(B193,Sheet2!A:C,3,FALSE) -> Joint and several accounts | N193: 0.1 | O193: 0.25 | P193: 1 | Q193: =F193*N193 -> 222210.87
A194: 46250 | B194: 8066682462 | C194: Legal | D194: Deceased | E194: Velile Tinto & Associates Inc | F194: 190218.26 | G194: 190212.51 | H194: 130 | I194: 1 | J194: late | K194: Deceased | L194: 72+ | M194: =VLOOKUP(B194,Sheet2!A:C,3,FALSE) -> Joint and several accounts | N194: 0.1 | O194: 0.25 | P194: 1 | Q194: =F194*N194 -> 19021.826
A195: 46250 | B195: 8066720838 | C195: Legal | D195: Deceased | F195: 1015439.5 | G195: 1006063.5 | H195: 100 | I195: 1 | J195: late | K195: Deceased | L195: 72+ | M195: =VLOOKUP(B195,Sheet2!A:C,3,FALSE) -> Joint and several accounts | N195: 0.1 | O195: 0.25 | P195: 1 | Q195: =F195*N195 -> 101543.95
A196: 46250 | B196: 8066736015 | C196: Legal | D196: Deceased | E196: Sandenberg Nel Haggard | F196: 1057339.4 | G196: 1057270.4 | H196: 117 | I196: 1 | J196: late | K196: Deceased | L196: 72+ | M196: =VLOOKUP(B196,Sheet2!A:C,3,FALSE) -> Joint and several accounts | N196: 0.1 | O196: 0.25 | P196: 1 | Q196: =F196*N196 -> 105733.94
A197: 46250 | B197: 8066751485 | C197: Legal | D197: Deceased | E197: Vezi & De Beer | F197: 558636.41 | G197: 558630.66 | H197: 108 | I197: 1 | J197: late | K197: Deceased | L197: 72+ | M197: =VLOOKUP(B197,Sheet2!A:C,3,FALSE) -> Private individuals | N197: 0.1 | O197: 0.25 | P197: 1 | Q197: =F197*N197 -> 55863.641
A198: 46250 | B198: 8066771716 | C198: Legal | D198: Charge_off_process | E198: Kemp and Associates | F198: 1116937.8 | G198: 457515.81 | H198: 72 | I198: 1 | J198: late | K198: Deceased | L198: 72+ | M198: =VLOOKUP(B198,Sheet2!A:C,3,FALSE) -> Private individuals | N198: 0.10678774 | O198: 0.25 | P198: 1 | Q198: =F198*N198 -> 119275.27
A199: 46250 | B199: 8066800486 | C199: Legal | D199: Deceased | E199: Kemp and Associates | F199: 360451.85 | G199: 310673.57 | H199: 99 | I199: 1 | J199: late | K199: Deceased | L199: 72+ | M199: =VLOOKUP(B199,Sheet2!A:C,3,FALSE) -> Private individuals | N199: 0.1 | O199: 0.25 | P199: 1 | Q199: =F199*N199 -> 36045.185
A200: 46250 | B200: 8066833530 | C200: Legal | D200: Deceased | E200: Velile Tinto & Associates Inc | F200: 1509579.6 | G200: 1400216.5 | H200: 116 | I200: 1 | J200: late | K200: Deceased | L200: 72+ | M200: =VLOOKUP(B200,Sheet2!A:C,3,FALSE) -> Joint and several accounts | N200: 0.1 | O200: 0.25 | P200: 1 | Q200: =F200*N200 -> 150957.96
A201: 46250 | B201: 8066923270 | C201: Legal | D201: Charge_off_process | E201: Strauss Daly Inc | F201: 2034160.3 | G201: 2034160.3 | H201: 126 | I201: 1 | J201: late | K201: Deceased | L201: 72+ | M201: =VLOOKUP(B201,Sheet2!A:C,3,FALSE) -> Joint and several accounts | N201: 0.1 | O201: 0.25 | P201: 1 | Q201: =F201*N201 -> 203416.03
A202: 46250 | B202: 8066938736 | C202: Legal | D202: Deceased | E202: Vezi & De Beer | F202: 202431.77 | G202: 202426.02 | H202: 165 | I202: 1 | J202: late | K202: Deceased | L202: 72+ | M202: =VLOOKUP(B202,Sheet2!A:C,3,FALSE) -> Joint and several accounts | N202: 0.1 | O202: 0.25 | P202: 1 | Q202: =F202*N202 -> 20243.177
A203: 46250 | B203: 8066959754 | C203: Legal | D203: Deceased | E203: Kemp and Associates | F203: 596872.33 | G203: 596866.58 | H203: 86 | I203: 1 | J203: late | K203: Deceased | L203: 72+ | M203: =VLOOKUP(B203,Sheet2!A:C,3,FALSE) -> Joint and several accounts | N203: 0.1 | O203: 0.25 | P203: 1 | Q203: =F203*N203 -> 59687.233
A204: 46250 | B204: 8067033234 | C204: Legal | D204: Deceased | E204: Velile Tinto & Associates Inc | F204: 1881556.1 | G204: 1881556.1 | H204: 99 | I204: 1 | J204: late | K204: Deceased | L204: 72+ | M204: =VLOOKUP(B204,Sheet2!A:C,3,FALSE) -> Joint and several accounts | N204: 0.1 | O204: 0.25 | P204: 1 | Q204: =F204*N204 -> 188155.61
A205: 46250 | B205: 8067067928 | C205: Legal | D205: Charge_off_process | E205: Vezi & De Beer | F205: 793951.71 | G205: 793945.96 | H205: 133 | I205: 1 | J205: late | K205: Deceased | L205: 72+ | M205: =VLOOKUP(B205,Sheet2!A:C,3,FALSE) -> Joint and several accounts | N205: 0.1 | O205: 0.25 | P205: 1 | Q205: =F205*N205 -> 79395.171
A206: 46250 | B206: 8067068584 | C206: Legal | D206: Deceased | E206: Velile Tinto & Associates Inc | F206: 489626.84 | G206: 489621.09 | H206: 128 | I206: 1 | J206: late | K206: Deceased | L206: 72+ | M206: =VLOOKUP(B206,Sheet2!A:C,3,FALSE) -> Joint and several accounts | N206: 0.1 | O206: 0.25 | P206: 1 | Q206: =F206*N206 -> 48962.684
A207: 46250 | B207: 8067076137 | C207: Legal | D207: Deceased | E207: Vezi & De Beer | F207: 222595.84 | G207: 222590.09 | H207: 81 | I207: 1 | J207: late | K207: Deceased | L207: 72+ | M207: =VLOOKUP(B207,Sheet2!A:C,3,FALSE) -> Joint and several accounts | N207: 0.18891131 | O207: 0.25 | P207: 1 | Q207: =F207*N207 -> 42050.872
... A253: 46250 | B253: 8069009291 | C253: Legal | D253: Deceased | E253: Kemp and Associates | F253: 1019475.1 | G253: 1019406.1 | H253: 70 | I253: 0 | J253: late | K253: Deceased | L253: 65-71 | M253: =VLOOKUP(B253,Sheet2!A:C,3,FALSE) -> Joint and several accounts | N253: 0.11460389 | O253: 0.25 | P253: 1 | Q253: =F253*N253 -> 116835.81
A254: 46250 | B254: 8069019676 | C254: Legal | D254: Deceased | F254: 309677.36 | G254: 309608.36 | H254: 130 | I254: 1 | J254: late | K254: Deceased | L254: 72+ | M254: =VLOOKUP(B254,Sheet2!A:C,3,FALSE) -> Joint and several accounts | N254: 0.1 | O254: 0.25 | P254: 1 | Q254: =F254*N254 -> 30967.736
A255: 46250 | B255: 8069023209 | C255: Legal | D255: Deceased | E255: Velile Tinto & Associates Inc | F255: 1367450.4 | G255: 1367381.4 | H255: 74 | I255: 1 | J255: late | K255: Deceased | L255: 72+ | M255: =VLOOKUP(B255,Sheet2!A:C,3,FALSE) -> Private individuals | N255: 0.21263338 | O255: 0.25 | P255: 1 | Q255: =F255*N255 -> 290765.61
A256: 46250 | B256: 8069079640 | C256: Legal | D256: Charge_off_process | E256: Sandenberg Nel Haggard | F256: 858348.7 | G256: 604864.39 | H256: 97 | I256: 1 | J256: late | K256: Deceased | L256: 72+ | M256: =VLOOKUP(B256,Sheet2!A:C,3,FALSE) -> Private individuals | N256: 0.1 | O256: 0.25 | P256: 1 | Q256: =F256*N256 -> 85834.87
A257: 46250 | B257: 8069116361 | C257: Legal | D257: Deceased | E257: Internal | F257: 271120.26 | G257: 221878.41 | H257: 78 | I257: 1 | J257: late | K257: Deceased | L257: 72+ | M257: =VLOOKUP(B257,Sheet2!A:C,3,FALSE) -> Private individuals | N257: 0.19590201 | O257: 0.25 | P257: 1 | Q257: =F257*N257 -> 53113.003
A258: 46250 | B258: 8069157725 | C258: Legal | D258: Deceased | E258: EG Cooper Majiedt Inc | F258: 445183.21 | G258: 445183.21 | H258: 110 | I258: 1 | J258: late | K258: Deceased | L258: 72+ | M258: =VLOOKUP(B258,Sheet2!A:C,3,FALSE) -> Joint and several accounts | N258: 0.1 | O258: 0.25 | P258: 1 | Q258: =F258*N258 -> 44518.321
A259: 46250 | B259: 8069222320 | C259: Legal | D259: Charge_off_process | E259: Bham & Dahya | F259: 298560.36 | G259: 298560.36 | H259: 72 | I259: 1 | J259: late | K259: Deceased | L259: 72+ | M259: =VLOOKUP(B259,Sheet2!A:C,3,FALSE) -> Joint and several accounts | N259: 0.21251955 | O259: 0.25 | P259: 1 | Q259: =F259*N259 -> 63449.915
A260: 46250 | B260: 8069254486 | C260: Legal | D260: Deceased | E260: Kemp and Associates | F260: 791659.86 | G260: 791659.86 | H260: 147 | I260: 1 | J260: late | K260: Deceased | L260: 72+ | M260: =VLOOKUP(B260,Sheet2!A:C,3,FALSE) -> Private individuals | N260: 0.1 | O260: 0.25 | P260: 1 | Q260: =F260*N260 -> 79165.986
A261: 46250 | B261: 8069283358 | C261: Legal | D261: Charge_off_process | E261: Strauss Daly Inc | F261: 319572.15 | G261: 319503.15 | H261: 90 | I261: 1 | J261: late | K261: Deceased | L261: 72+ | M261: =VLOOKUP(B261,Sheet2!A:C,3,FALSE) -> Joint and several accounts | N261: 0.1 | O261: 0.25 | P261: 1 | Q261: =F261*N261 -> 31957.215
A262: 46250 | B262: 8069407352 | C262: Legal | D262: Deceased | F262: 1032875.4 | G262: 1032875.4 | H262: 90 | I262: 1 | J262: late | K262: Deceased | L262: 72+ | M262: =VLOOKUP(B262,Sheet2!A:C,3,FALSE) -> Private individuals | N262: 0.1 | O262: 0.25 | P262: 1 | Q262: =F262*N262 -> 103287.54
A263: 46250 | B263: 8069417436 | C263: Legal | D263: Deceased | E263: Velile Tinto & Associates Inc | F263: 1499396.3 | G263: 1499396.3 | H263: 126 | I263: 1 | J263: late | K263: Deceased | L263: 72+ | M263: =VLOOKUP(B263,Sheet2!A:C,3,FALSE) -> Private individuals | N263: 0.1 | O263: 0.25 | P263: 1 | Q263: =F263*N263 -> 149939.63
A264: 46250 | B264: 8069443130 | C264: Legal | D264: Charge_off_process | E264: Strauss Daly Inc | F264: 188892.01 | G264: 188892.01 | H264: 71 | I264: 0 | J264: late | K264: Deceased | L264: 65-71 | M264: =VLOOKUP(B264,Sheet2!A:C,3,FALSE) -> Joint and several accounts | N264: 0.11067657 | O264: 0.25 | P264: 1 | Q264: =F264*N264 -> 20905.92
A265: 46250 | B265: 8069449500 | C265: Legal | D265: Deceased | F265: 710954.91 | G265: 710954.91 | H265: 93 | I265: 1 | J265: late | K265: Deceased | L265: 72+ | M265: =VLOOKUP(B265,Sheet2!A:C,3,FALSE) -> Private individuals | N265: 0.11863037 | O265: 0.25 | P265: 1 | Q265: =F265*N265 -> 84340.848
A266: 46250 | B266: 8069470068 | C266: Legal | D266: Deceased | E266: Vezi & De Beer | F266: 265164.22 | G266: 265164.22 | H266: 72 | I266: 1 | J266: late | K266: Deceased | L266: 72+ | M266: =VLOOKUP(B266,Sheet2!A:C,3,FALSE) -> Joint and several accounts | N266: 0.10678774 | O266: 0.25 | P266: 1 | Q266: =F266*N266 -> 28316.288
A267: 46250 | B267: 8069498981 | C267: Legal | D267: Deceased | E267: Internal | F267: 1350789.3 | G267: 1350789.3 | H267: 106 | I267: 1 | J267: late | K267: Deceased | L267: 72+ | M267: =VLOOKUP(B267,Sheet2!A:C,3,FALSE) -> Private individuals | N267: 0.1 | O267: 0.25 | P267: 1 | Q267: =F267*N267 -> 135078.93
A268: 46250 | B268: 8069528940 | C268: Legal | D268: Charge_off_process | E268: Bham & Dahya | F268: 1335139.8 | G268: 1335139.8 | H268: 99 | I268: 1 | J268: late | K268: Deceased | L268: 72+ | M268: =VLOOKUP(B268,Sheet2!A:C,3,FALSE) -> Private individuals | N268: 0.1 | O268: 0.25 | P268: 1 | Q268: =F268*N268 -> 133513.98
A269: 46250 | B269: 8069598666 | C269: Legal | D269: Charge_off_process | E269: Smit Sewgoolam | F269: 1056370.9 | G269: 1056370.9 | H269: 121 | I269: 1 | J269: late | K269: Deceased | L269: 72+ | M269: =VLOOKUP(B269,Sheet2!A:C,3,FALSE) -> Private individuals | N269: 0.1 | O269: 0.25 | P269: 1 | Q269: =F269*N269 -> 105637.09
A270: 46250 | B270: 8069615967 | C270: Legal | D270: Charge_off_process | E270: Velile Tinto & Associates Inc | F270: 766485.63 | G270: 766416.63 | H270: 92 | I270: 1 | J270: late | K270: Deceased | L270: 72+ | M270: =VLOOKUP(B270,Sheet2!A:C,3,FALSE) -> Joint and several accounts | N270: 0.1 | O270: 0.25 | P270: 1 | Q270: =F270*N270 -> 76648.563
A271: 46250 | B271: 8069639828 | C271: Legal | D271: Deceased | E271: Vezi & De Beer | F271: 1290137.9 | G271: 1164272.6 | H271: 120 | I271: 1 | J271: late | K271: Deceased | L271: 72+ | M271: =VLOOKUP(B271,Sheet2!A:C,3,FALSE) -> Private individuals | N271: 0.1 | O271: 0.25 | P271: 1 | Q271: =F271*N271 -> 129013.79
A272: 46250 | B272: 8069737967 | C272: Legal | D272: Deceased | E272: Internal | F272: 455172.62 | G272: 455172.62 | H272: 108 | I272: 1 | J272: late | K272: Deceased | L272: 72+ | M272: =VLOOKUP(B272,Sheet2!A:C,3,FALSE) -> Joint and several accounts | N272: 0.1 | O272: 0.25 | P272: 1 | Q272: =F272*N272 -> 45517.262
A273: 46250 | B273: 8069794713 | C273: Legal | D273: Charge_off_process | E273: Velile Tinto & Associates Inc | F273: 533934.52 | G273: 533865.52 | H273: 130 | I273: 1 | J273: late | K273: Deceased | L273: 72+ | M273: =VLOOKUP(B273,Sheet2!A:C,3,FALSE) -> Joint and several accounts | N273: 0.1 | O273: 0.25 | P273: 1 | Q273: =F273*N273 -> 53393.452
A274: 46250 | B274: 8069859307 | C274: Legal | D274: Charge_off_process | E274: Smit Sewgoolam | F274: 201768.17 | G274: 201699.17 | H274: 81 | I274: 1 | J274: late | K274: Deceased | L274: 72+ | M274: =VLOOKUP(B274,Sheet2!A:C,3,FALSE) -> Joint and several accounts | N274: 0.18251272 | O274: 0.25 | P274: 1 | Q274: =F274*N274 -> 36825.258
A275: 46250 | B275: 8069888643 | C275: Legal | D275: Deceased | E275: Velile Tinto & Associates Inc | F275: 1295248.1 | G275: 1295179.1 | H275: 101 | I275: 1 | J275: late | K275: Deceased | L275: 72+ | M275: =VLOOKUP(B275,Sheet2!A:C,3,FALSE) -> Joint and several accounts | N275: 0.1 | O275: 0.25 | P275: 1 | Q275: =F275*N275 -> 129524.81
A276: 46250 | B276: 8069913199 | C276: Legal | D276: Deceased | E276: Kemp and Associates | F276: 530590.57 | G276: 530521.57 | H276: 113 | I276: 1 | J276: late | K276: Deceased | L276: 72+ | M276: =VLOOKUP(B276,Sheet2!A:C,3,FALSE) -> Joint and several accounts | N276: 0.1 | O276: 0.25 | P276: 1 | Q276: =F276*N276 -> 53059.057
A277: 46250 | B277: 8069919860 | C277: Legal | D277: Deceased | E277: Vezi & De Beer | F277: 1901841.3 | G277: 1282690.9 | H277: 99 | I277: 1 | J277: late | K277: Deceased | L277: 72+ | M277: =VLOOKUP(B277,Sheet2!A:C,3,FALSE) -> Private individuals | N277: 0.1 | O277: 0.25 | P277: 1 | Q277: =F277*N277 -> 190184.13
... A306: 46250 | B306: 8070771661 | C306: Legal | D306: Deceased | E306: Velile Tinto & Associates Inc | F306: 164419.46 | G306: 164419.46 | H306: 95 | I306: 1 | J306: late | K306: Deceased | L306: 72+ | M306: =VLOOKUP(B306,Sheet2!A:C,3,FALSE) -> Private individuals | N306: 0.1 | O306: 0.25 | P306: 1 | Q306: =F306*N306 -> 16441.946
A307: 46250 | B307: 8070850970 | C307: Legal | E307: Sandenberg Nel Haggard | F307: 1131886.8 | G307: 1131886.8 | H307: 130 | I307: 1 | J307: late | K307: Deceased | L307: 72+ | M307: =VLOOKUP(B307,Sheet2!A:C,3,FALSE) -> Joint and several accounts | N307: 0.1 | O307: 0.25 | P307: 1 | Q307: =F307*N307 -> 113188.68
A308: 46250 | B308: 8070857613 | C308: Legal | D308: Charge_off_process | E308: Bham & Dahya | F308: 586908.25 | G308: 320944.93 | H308: 92 | I308: 1 | J308: late | K308: Deceased | L308: 72+ | M308: =VLOOKUP(B308,Sheet2!A:C,3,FALSE) -> Private individuals | N308: 0.1 | O308: 0.25 | P308: 1 | Q308: =F308*N308 -> 58690.825
A309: 46250 | B309: 8070895493 | C309: Legal | D309: Deceased | E309: Kemp and Associates | F309: 1223002.9 | G309: 1222933.9 | H309: 115 | I309: 1 | J309: late | K309: Deceased | L309: 72+ | M309: =VLOOKUP(B309,Sheet2!A:C,3,FALSE) -> Private individuals | N309: 0.1 | O309: 0.25 | P309: 1 | Q309: =F309*N309 -> 122300.29
...
